setup.py
src/rdcache/__init__.py
src/rdcache/cache.py
src/rdcache/dummy.py
src/rdcache/ext.py
src/rdcache/utils.py
src/rdcache/wrapper.py
src/rdcache.egg-info/PKG-INFO
src/rdcache.egg-info/SOURCES.txt
src/rdcache.egg-info/dependency_links.txt
src/rdcache.egg-info/requires.txt
src/rdcache.egg-info/top_level.txt