Metadata-Version: 1.1
Name: rdcache
Version: 1.1.5
Summary: caching for humans, forked from jneen/python-cache
Home-page: https://github.com/azhai/rdcache
Author: Jay Adkisson, Ryan Liu
Author-email: azhai (at) 126 (dot) com
License: MIT
Keywords: cache,decorator
Platform: UNKNOWN
Classifier: Development Status :: 5 - Production/Stable
Classifier: Environment :: Web Environment
Classifier: Intended Audience :: Developers
Classifier: Topic :: Database :: Front-Ends
Classifier: License :: OSI Approved :: MIT License
